langchain_cognee/.DS_Store
langchain_cognee/__init__.py
langchain_cognee/py.typed
langchain_cognee/retrievers copy.py
langchain_cognee/retrievers.py
langchain_cognee-0.1.1.dist-info/LICENSE
langchain_cognee-0.1.1.dist-info/METADATA
langchain_cognee-0.1.1.dist-info/WHEEL
langchain_cognee-0.1.1.dist-info/RECORD
